neuraparse-0.3.6-py3.12-nspkg.pth
neuraparse/universal_scraper/__init__.py
neuraparse/universal_scraper/base_scraper.py
neuraparse/universal_scraper/main.py
neuraparse/universal_scraper/models.py
neuraparse/universal_scraper/multi_scraper.py
neuraparse/universal_scraper/scraper.py
neuraparse-0.3.6.dist-info/METADATA
neuraparse-0.3.6.dist-info/WHEEL
neuraparse-0.3.6.dist-info/entry_points.txt
neuraparse-0.3.6.dist-info/namespace_packages.txt
neuraparse-0.3.6.dist-info/top_level.txt
neuraparse-0.3.6.dist-info/RECORD
